mlops_local/__init__.py
mlops_local/cli.py
mlops_local-1.0.6.dist-info/METADATA
mlops_local-1.0.6.dist-info/WHEEL
mlops_local-1.0.6.dist-info/entry_points.txt
mlops_local-1.0.6.dist-info/top_level.txt
mlops_local-1.0.6.dist-info/RECORD
