Metadata-Version: 2.1
Name: mlops-local
Version: 1.0.6
Summary: Package to test preprocessing and ML scripts locally before pushing to the MLOps platform
Home-page: UNKNOWN
Author: Petter Hultin Gustafsson
Author-email: petter@mlops.cloud
License: UNKNOWN
Platform: UNKNOWN
Classifier: Programming Language :: Python :: 3
Classifier: License :: OSI Approved :: MIT License
Classifier: Operating System :: OS Independent
Requires-Python: >=3.6
Requires-Dist: Click
Requires-Dist: docker
